MANIFEST.in
README.txt
setup.py
docs/HISTORY.txt
docs/LICENSE.txt
src/silva/__init__.py
src/silva.core.smi.egg-info/PKG-INFO
src/silva.core.smi.egg-info/SOURCES.txt
src/silva.core.smi.egg-info/dependency_links.txt
src/silva.core.smi.egg-info/namespace_packages.txt
src/silva.core.smi.egg-info/not-zip-safe
src/silva.core.smi.egg-info/requires.txt
src/silva.core.smi.egg-info/top_level.txt
src/silva/core/__init__.py
src/silva/core/smi/__init__.py
src/silva/core/smi/about.py
src/silva/core/smi/admin.py
src/silva/core/smi/configure.zcml
src/silva/core/smi/preview.py
src/silva/core/smi/userinfo.py
src/silva/core/smi/view.py
src/silva/core/smi/about_templates/about.cpt
src/silva/core/smi/admin_templates/configurationscreen.cpt
src/silva/core/smi/content/__init__.py
src/silva/core/smi/content/adding.py
src/silva/core/smi/content/container.py
src/silva/core/smi/content/metadata.py
src/silva/core/smi/content/publishingactions.py
src/silva/core/smi/content/adding_templates/addinginformation.cpt
src/silva/core/smi/content/metadata_templates/contentreferencedby.cpt
src/silva/core/smi/content/metadata_templates/metadataform.cpt
src/silva/core/smi/content/publish/__init__.py
src/silva/core/smi/content/publish/container.py
src/silva/core/smi/content/publish/management.py
src/silva/core/smi/content/publish/portlet.py
src/silva/core/smi/content/publish/status.py
src/silva/core/smi/content/publish/usecase.txt
src/silva/core/smi/content/publish/management_templates/requestforapprovalstatusdisplayform.cpt
src/silva/core/smi/content/publish/portlet_templates/publicationinfo.cpt
src/silva/core/smi/content/publish/status_templates/versioningstatewidget.cpt
src/silva/core/smi/content/static/compare.css
src/silva/core/smi/content/static/edit.png
src/silva/core/smi/content/xml/__init__.py
src/silva/core/smi/content/xml/errors.py
src/silva/core/smi/content/xml/export.py
src/silva/core/smi/content/xml/import.py
src/silva/core/smi/content/xml/errors_templates/externalreferenceerrorpage.cpt
src/silva/core/smi/errors/__init__.py
src/silva/core/smi/errors/quota.py
src/silva/core/smi/errors/references.py
src/silva/core/smi/errors/quota_templates/overquotaerror.cpt
src/silva/core/smi/errors/references_templates/break_references.cpt
src/silva/core/smi/settings/__init__.py
