Metadata-Version: 1.1
Name: silva.core.smi
Version: 3.0.3
Summary: Silva Management Interface
Home-page: https://github.com/silvacms/silva.core.smi
Author: Infrae
Author-email: info@infrae.com
License: BSD
Keywords: silva zope2 smi
Platform: UNKNOWN
Classifier: Framework :: Zope2
Classifier: License :: OSI Approved :: BSD License
Classifier: Programming Language :: Python
Classifier: Topic :: Software Development :: Libraries :: Python Modules
